{
  "appId": "sparklab",
  "version": "0.4.2",
  "channel": "main",
  "releasedAt": "2026-06-09T05:42:36+08:00",
  "title": "更新进度与完成后自动刷新",
  "mandatory": false,
  "announcement": {
    "enabled": true,
    "level": "info",
    "title": "SparkLab 更新状态可视化已启用",
    "message": "管理员点击更新后，后台会显示拉取代码、构建镜像、重启服务等进度；更新完成后页面会自动刷新到新版本。"
  },
  "changelog": [
    {
      "version": "0.4.2",
      "date": "2026-06-09",
      "title": "更新进度与自动刷新",
      "items": [
        "新增管理员更新状态接口，更新阶段会写入持久化状态文件，服务重启后仍能继续判断完成状态。",
        "管理后台点击更新后自动轮询更新状态，展示拉取代码、构建镜像和重启服务进度。",
        "更新完成后前端会倒计时并自动刷新页面，避免停留在旧版本界面。",
        "新增 SPARKLAB_UPDATE_DIR 配置，默认把更新状态和重启日志写入 /app/data。"
      ]
    },
    {
      "version": "0.4.1",
      "date": "2026-06-09",
      "title": "切换为本机 Docker 单节点管理",
      "items": [
        "后端自动维护一个本机 Docker 节点，统一使用 unix:///var/run/docker.sock。",
        "移除管理侧边栏中的服务器管理入口，不再引导添加远程 Docker 服务器。",
        "服务器状态页改为本机 Docker 状态页，去掉远程地址、2375 端口和添加服务器表单。",
        "容器、镜像、网络和存储页面继续复用本机 Docker 节点，不需要额外配置服务器。"
      ]
    },
    {
      "version": "0.4.0",
      "date": "2026-06-09",
      "title": "新增 Docker-only 部署与更新",
      "items": [
        "新增根目录 docker-compose.yml、后端 Dockerfile、前端 Dockerfile 和统一 .env.example。",
        "更新脚本改为 Docker Compose 构建镜像并后台重启服务，不再依赖宿主机 Go 或 Node 构建。",
        "后端容器挂载宿主机仓库与 Docker socket，可通过管理后台从 GitHub 拉取最新代码并完成重部署。",
        "前端容器代理改用 SERVER_URL 访问后端，浏览器侧继续通过公开端口连接 WebSocket。"
      ]
    },
    {
      "version": "0.3.0",
      "date": "2026-06-09",
      "title": "完善 GitHub 更新机制",
      "items": [
        "新增 update-manifest.json 发布清单，使用版本号和更新日志判断更新。",
        "新增前端全局公告/更新提示，进入前端时自动检查一次。",
        "管理员可检查更新并执行安全的 fast-forward 拉取与更新脚本。",
        "Docker 管理改为默认使用本机 unix:///var/run/docker.sock。"
      ]
    }
  ],
  "scripts": {
    "linux": "scripts/update.sh",
    "windows": "scripts/update.ps1"
  }
}
